{
    "global":     {
        "modelName": "com.landray.kmss.sys.property.model.SysPropertyDbColumn",
        "messageKey" : "sys-property:table.sysPropertyDbColumn",
        "table": "sys_property_db_column",
        "displayProperty": "fdName"
    },
    "attrs":     {
        "fdId":         {
            "propertyType": "id",
            "generator": {"type": "assigned"}
        },
        "fdIsPk":         {
            "propertyType": "simple",
            "messageKey" : "sys-property:sysPropertyDbColumn.fdIsPk",
            "type": "Boolean",
            "column": "fd_is_pk"
        },
        "fdModelName":         {
            "propertyType": "simple",
            "messageKey" : "sys-property:sysPropertyDbColumn.fdModelName",
            "canDisplay": "false",
            "type": "String",
            "column": "fd_model_name",
            "length": "200"
        },
        "fdType":         {
            "propertyType": "simple",
            "messageKey" : "sys-property:sysPropertyDbColumn.fdType",
            "type": "String",
            "column": "fd_type",
            "length": "200"
        },
        "fdName":         {
            "propertyType": "simple",
            "messageKey" : "sys-property:sysPropertyDbColumn.fdName",
            "type": "String",
            "column": "fd_name",
            "length": "200"
        },
        "fdColumn":         {
            "propertyType": "simple",
            "messageKey" : "sys-property:sysPropertyDbColumn.fdColumn",
            "type": "String",
            "column": "fd_column",
            "length": "50"
        },
        "fdLength":         {
            "propertyType": "simple",
            "messageKey" : "sys-property:sysPropertyDbColumn.fdLength",
            "type": "Integer",
            "column": "fd_length",
            "length": "5"
        },
        "fdTableName":         {
            "propertyType": "simple",
            "messageKey" : "sys-property:sysPropertyDbColumn.fdTableName",
            "type": "String",
            "column": "fd_table_name",
            "length": "50"
        },
        "fdMainColumn":         {
            "propertyType": "simple",
            "messageKey" : "sys-property:sysPropertyDbColumn.fdMainColumn",
            "type": "String",
            "column": "fd_main_column",
            "length": "200"
        },
        "fdElementColumn":         {
            "propertyType": "simple",
            "messageKey" : "sys-property:sysPropertyDbColumn.fdElementColumn",
            "type": "String",
            "column": "fd_element_column",
            "length": "200"
        },
        "fdRelation":         {
            "propertyType": "simple",
            "messageKey" : "sys-property:sysPropertyDbColumn.fdRelation",
            "type": "String",
            "column": "fd_relation",
            "length": "50"
        },
        "fdOrder":         {
            "propertyType": "simple",
            "messageKey" : "sys-property:sysPropertyDbColumn.fdOrder",
            "type": "Integer",
            "column": "fd_order",
            "length": "10"
        },
        "fdParent":         {
            "propertyType": "model",
            "messageKey" : "sys-property:sysPropertyDbColumn.fdParent",
            "type": "com.landray.kmss.sys.property.model.SysPropertyDbTable",
            "column": "fd_main_id",
            "notNull": "true"
        },
        "fdIsEnable":         {
            "propertyType": "simple",
            "messageKey" : "sys-property:sysPropertyDbColumn.fdIsEnable",
            "type": "Boolean",
            "column": "fd_is_enable"
        }
    }
}