<?xml version="1.0" encoding="UTF-8"?>
<column-enums>
	<type 
        name="eop_basedata_mate_status">
        <value-label>
            <value>0</value>
            <label-key>enums.mate_status.0</label-key>
            <bundle>eop-basedata</bundle>
        </value-label>
        <value-label>
            <value>1</value>
            <label-key>enums.mate_status.1</label-key>
            <bundle>eop-basedata</bundle>
        </value-label>
    </type>
    <type
            name="eop_basedata_fd_contract_account_type">
        <value-label>
            <value>1</value>
            <label-key>enums.fd_contract_account_type.1</label-key>
            <bundle>eop-basedata</bundle>
        </value-label>
        <value-label>
            <value>2</value>
            <label-key>enums.fd_contract_account_type.2</label-key>
            <bundle>eop-basedata</bundle>
        </value-label>
    </type>
	<type
        name="eop_basedata_fd_ocr_company">
        <value-label>
            <value>1</value>
            <label-key>enums.fd_ocr_company.1</label-key>
            <bundle>eop-basedata</bundle>
        </value-label>
        <value-label>
            <value>2</value>
            <label-key>enums.fd_ocr_company.2</label-key>
            <bundle>eop-basedata</bundle>
        </value-label>
    </type>
    <type
            name="eop_basedata_fd_inv_ver_cpy">
        <value-label>
            <value>1</value>
            <label-key>enums.fd_inv_ver_cpy.1</label-key>
            <bundle>eop-basedata</bundle>
        </value-label>
        <value-label>
            <value>2</value>
            <label-key>enums.fd_inv_ver_cpy.2</label-key>
            <bundle>eop-basedata</bundle>
        </value-label>
    </type>
    <type 
        name="eop_basedata_berth_level">
        <value-label>
            <value>1</value>
            <label-key>enums.berth_level.1</label-key>
            <bundle>eop-basedata</bundle>
        </value-label>
        <value-label>
            <value>2</value>
            <label-key>enums.berth_level.2</label-key>
            <bundle>eop-basedata</bundle>
        </value-label>
        <value-label>
            <value>3</value>
            <label-key>enums.berth_level.3</label-key>
            <bundle>eop-basedata</bundle>
        </value-label>
        <value-label>
            <value>4</value>
            <label-key>enums.berth_level.4</label-key>
            <bundle>eop-basedata</bundle>
        </value-label>
        <value-label>
            <value>5</value>
            <label-key>enums.berth_level.5</label-key>
            <bundle>eop-basedata</bundle>
        </value-label>
    </type>
    <type 
        name="eop_basedata_area_type">
        <value-label>
            <value>1</value>
            <label-key>enums.area_type.1</label-key>
            <bundle>eop-basedata</bundle>
        </value-label>
        <value-label>
            <value>2</value>
            <label-key>enums.area_type.2</label-key>
            <bundle>eop-basedata</bundle>
        </value-label>
        <value-label>
            <value>3</value>
            <label-key>enums.area_type.3</label-key>
            <bundle>eop-basedata</bundle>
        </value-label>
    </type>
    <type 
        name="eop_basedata_cost_type">
        <value-label>
            <value>1</value>
            <label-key>enums.cost_type.1</label-key>
            <bundle>eop-basedata</bundle>
        </value-label>
        <value-label>
            <value>2</value>
            <label-key>enums.cost_type.2</label-key>
            <bundle>eop-basedata</bundle>
        </value-label>
    </type>
    <type 
        name="eop_basedata_is_default_account">
        <value-label>
            <value>0</value>
            <label-key>enums.is_default_account.0</label-key>
            <bundle>eop-basedata</bundle>
        </value-label>
        <value-label>
            <value>1</value>
            <label-key>enums.is_default_account.1</label-key>
            <bundle>eop-basedata</bundle>
        </value-label>
    </type>
    <type 
        name="eop_basedata_dimension_type">
        <value-label>
            <value>1</value>
            <label-key>enums.dimension_type.1</label-key>
            <bundle>eop-basedata</bundle>
        </value-label>
        <!-- <value-label>
            <value>2</value>
            <label-key>enums.dimension_type.2</label-key>
            <bundle>eop-basedata</bundle>
        </value-label> -->
    </type>
    <type 
        name="eop_basedata_dimension_target">
        <value-label>
            <value>1</value>
            <label-key>enums.dimension_target.1</label-key>
            <bundle>eop-basedata</bundle>
        </value-label>
        <value-label>
            <value>2</value>
            <label-key>enums.dimension_target.2</label-key>
            <bundle>eop-basedata</bundle>
        </value-label>
    </type>
    <type 
        name="eop_basedata_budget_period">
        <value-label>
            <value>1</value>
            <label-key>enums.budget_period.1</label-key>
            <bundle>eop-basedata</bundle>
        </value-label>
        <value-label>
            <value>2</value>
            <label-key>enums.budget_period.2</label-key>
            <bundle>eop-basedata</bundle>
        </value-label>
        <value-label>
            <value>3</value>
            <label-key>enums.budget_period.3</label-key>
            <bundle>eop-basedata</bundle>
        </value-label>
        <value-label>
            <value>4</value>
            <label-key>enums.budget_period.4</label-key>
            <bundle>eop-basedata</bundle>
        </value-label>
    </type>
    <type 
        name="eop_basedata_budget_rule_period">
        <!-- <value-label>
            <value>1</value>
            <label-key>enums.budget_rule_period.1</label-key>
            <bundle>eop-basedata</bundle>
        </value-label> -->
        <value-label>
            <value>2</value>
            <label-key>enums.budget_rule_period.2</label-key>
            <bundle>eop-basedata</bundle>
        </value-label>
        <value-label>
            <value>3</value>
            <label-key>enums.budget_rule_period.3</label-key>
            <bundle>eop-basedata</bundle>
        </value-label>
        <value-label>
            <value>4</value>
            <label-key>enums.budget_rule_period.4</label-key>
            <bundle>eop-basedata</bundle>
        </value-label>
    </type>
    <type 
        name="eop_basedata_supplier_type">
        <value-label>
            <value>1</value>
            <label-key>enums.supplier_type.1</label-key>
            <bundle>eop-basedata</bundle>
        </value-label>
        <value-label>
            <value>2</value>
            <label-key>enums.supplier_type.2</label-key>
            <bundle>eop-basedata</bundle>
        </value-label>
        <value-label>
            <value>3</value>
            <label-key>enums.supplier_type.3</label-key>
            <bundle>eop-basedata</bundle>
        </value-label>
    </type>
    <type 
        name="eop_basedata_cost_item">
        <value-label>
            <value>1</value>
            <label-key>enums.cost_item.1</label-key>
            <bundle>eop-basedata</bundle>
        </value-label>
        <value-label>
            <value>2</value>
            <label-key>enums.cost_item.2</label-key>
            <bundle>eop-basedata</bundle>
        </value-label>
        <value-label>
            <value>3</value>
            <label-key>enums.cost_item.3</label-key>
            <bundle>eop-basedata</bundle>
        </value-label>
        <value-label>
            <value>4</value>
            <label-key>enums.cost_item.4</label-key>
            <bundle>eop-basedata</bundle>
        </value-label>
        <value-label>
            <value>5</value>
            <label-key>enums.cost_item.5</label-key>
            <bundle>eop-basedata</bundle>
        </value-label>
        <value-label>
            <value>6</value>
            <label-key>enums.cost_item.6</label-key>
            <bundle>eop-basedata</bundle>
        </value-label>
        <value-label>
            <value>7</value>
            <label-key>enums.cost_item.7</label-key>
            <bundle>eop-basedata</bundle>
        </value-label>
        <value-label>
            <value>8</value>
            <label-key>enums.cost_item.8</label-key>
            <bundle>eop-basedata</bundle>
        </value-label>
        <value-label>
            <value>9</value>
            <label-key>enums.cost_item.9</label-key>
            <bundle>eop-basedata</bundle>
        </value-label>
        <value-label>
            <value>10</value>
            <label-key>enums.cost_item.10</label-key>
            <bundle>eop-basedata</bundle>
        </value-label>
        <value-label>
            <value>11</value>
            <label-key>enums.cost_item.11</label-key>
            <bundle>eop-basedata</bundle>
        </value-label>
    </type>
    <type 
        name="eop_basedata_standard_dimension">
        <value-label>
            <value>1</value>
            <label-key>enums.standard_dimension.1</label-key>
            <bundle>eop-basedata</bundle>
        </value-label>
        <value-label>
            <value>2</value>
            <label-key>enums.standard_dimension.2</label-key>
            <bundle>eop-basedata</bundle>
        </value-label>
        <value-label>
            <value>6</value>
            <label-key>enums.standard_dimension.6</label-key>
            <bundle>eop-basedata</bundle>
        </value-label>
        <value-label>
            <value>3</value>
            <label-key>enums.standard_dimension.3</label-key>
            <bundle>eop-basedata</bundle>
        </value-label>
        <value-label>
            <value>4</value>
            <label-key>enums.standard_dimension.4</label-key>
            <bundle>eop-basedata</bundle>
        </value-label>
        <value-label>
            <value>5</value>
            <label-key>enums.standard_dimension.5</label-key>
            <bundle>eop-basedata</bundle>
        </value-label>
    </type>
    <type 
        name="eop_basedata_standard_type">
        <value-label>
            <value>1</value>
            <label-key>enums.standard_type.1</label-key>
            <bundle>eop-basedata</bundle>
        </value-label>
        <value-label>
            <value>2</value>
            <label-key>enums.standard_type.2</label-key>
            <bundle>eop-basedata</bundle>
        </value-label>
        <value-label>
            <value>3</value>
            <label-key>enums.standard_type.3</label-key>
            <bundle>eop-basedata</bundle>
        </value-label>
        <value-label>
            <value>4</value>
            <label-key>enums.standard_type.4</label-key>
            <bundle>eop-basedata</bundle>
        </value-label>
    </type>
    <type 
        name="eop_basedata_standard_target">
        <value-label>
            <value>1</value>
            <label-key>enums.standard_target.1</label-key>
            <bundle>eop-basedata</bundle>
        </value-label>
        <value-label>
            <value>2</value>
            <label-key>enums.standard_target.2</label-key>
            <bundle>eop-basedata</bundle>
        </value-label>
    </type>
    <type 
        name="eop_basedata_standard_forbid">
        <value-label>
            <value>1</value>
            <label-key>enums.standard_forbid.1</label-key>
            <bundle>eop-basedata</bundle>
        </value-label>
        <value-label>
            <value>2</value>
            <label-key>enums.standard_forbid.2</label-key>
            <bundle>eop-basedata</bundle>
        </value-label>
    </type>
    <type 
        name="eop_basedata_item_field">
        <value-label>
            <value>fdVatInvoice</value>
            <label-key>enums.item_field.fdVatInvoice</label-key>
            <bundle>eop-basedata</bundle>
            <label>增值税专用发票</label>
        </value-label>
        <value-label>
            <value>fdInvoiceNumber</value>
            <label-key>enums.item_field.fdInvoiceNumber</label-key>
            <bundle>eop-basedata</bundle>
            <label>发票号码</label>
        </value-label>
        <value-label>
            <value>fdInvoiceCompany</value>
            <label-key>enums.item_field.fdInvoiceCompany</label-key>
            <bundle>eop-basedata</bundle>
            <label>开票公司</label>
        </value-label>
        <value-label>
            <value>fdInvoiceMoney</value>
            <label-key>enums.item_field.fdInvoiceMoney</label-key>
            <bundle>eop-basedata</bundle>
            <label>发票金额</label>
        </value-label>
        <value-label>
            <value>fdTaxRate</value>
            <label-key>enums.item_field.fdTaxRate</label-key>
            <bundle>eop-basedata</bundle>
            <label>税率</label>
        </value-label>
        <value-label>
            <value>fdTaxMoney</value>
            <label-key>enums.item_field.fdTaxMoney</label-key>
            <bundle>eop-basedata</bundle>
            <label>税额</label>
        </value-label>
        <value-label>
            <value>fdNoTaxMoney</value>
            <label-key>enums.item_field.fdNoTaxMoney</label-key>
            <bundle>eop-basedata</bundle>
            <label>不含税金额</label>
        </value-label>
        <value-label>
            <value>fdTravelStart</value>
            <label-key>enums.item_field.fdTravelStart</label-key>
            <bundle>eop-basedata</bundle>
            <label>出发地</label>
        </value-label>
        <value-label>
            <value>fdTravelArrive</value>
            <label-key>enums.item_field.fdTravelArrive</label-key>
            <bundle>eop-basedata</bundle>
            <label>到达地</label>
        </value-label>
        <value-label>
            <value>fdExchangeRate</value>
            <label-key>enums.item_field.fdExchangeRate</label-key>
            <bundle>eop-basedata</bundle>
            <label>汇率</label>
        </value-label>
        <value-label>
            <value>fdCurrencyMoney</value>
            <label-key>enums.item_field.fdCurrencyMoney</label-key>
            <bundle>eop-basedata</bundle>
            <label>本币金额</label>
        </value-label>
        <value-label>
            <value>fdWbs</value>
            <label-key>enums.item_field.fdWbs</label-key>
            <bundle>eop-basedata</bundle>
            <label>WBS号</label>
        </value-label>
        <value-label>
            <value>fdInnerOrder</value>
            <label-key>enums.item_field.fdInnerOrder</label-key>
            <bundle>eop-basedata</bundle>
            <label>内部订单</label>
        </value-label>
    </type>
    <type 
        name="eop_basedata_exchange_rate_type">
        <value-label>
            <value>1</value>
            <label-key>enums.exchange_rate_type.1</label-key>
            <bundle>eop-basedata</bundle>
        </value-label>
        <value-label>
            <value>2</value>
            <label-key>enums.exchange_rate_type.2</label-key>
            <bundle>eop-basedata</bundle>
        </value-label>
    </type>
    <type 
        name="eop_basedata_switch_paymentIntegration_type">
        <value-label>
            <value>1</value>
            <label-key>enums.switch.paymentIntegration_type1</label-key>
            <bundle>eop-basedata</bundle>
        </value-label>
        <value-label>
            <value>2</value>
            <label-key>enums.switch.paymentIntegration_type2</label-key>
            <bundle>eop-basedata</bundle>
        </value-label>
        <value-label>
            <value>3</value>
            <label-key>enums.switch.paymentIntegration_type3</label-key>
            <bundle>eop-basedata</bundle>
        </value-label>
    </type>
    <type 
        name="eop_basedata_switch_financialSystem">
        <value-label>
            <value>U8</value>
            <label-key>enums.switch.financialSystem_U8</label-key>
            <bundle>eop-basedata</bundle>
        </value-label>
        <value-label>
            <value>K3</value>
            <label-key>enums.switch.financialSystem_K3</label-key>
            <bundle>eop-basedata</bundle>
        </value-label>
        <value-label>
            <value>EAS</value>
            <label-key>enums.switch.financialSystem_EAS</label-key>
            <bundle>eop-basedata</bundle>
        </value-label>
        <value-label>
            <value>Oracle</value>
            <label-key>enums.switch.financialSystem_Oracle</label-key>
            <bundle>eop-basedata</bundle>
        </value-label>
        <value-label>
            <value>SAP</value>
            <label-key>enums.switch.financialSystem_SAP</label-key>
            <bundle>eop-basedata</bundle>
        </value-label>
        <value-label>
            <value>NC</value>
            <label-key>enums.switch.financialSystem_NC</label-key>
            <bundle>eop-basedata</bundle>
        </value-label>
          <value-label>
            <value>K3Cloud</value>
            <label-key>enums.switch.financialSystem_K3Cloud</label-key>
            <bundle>eop-basedata</bundle>
        </value-label>
    </type>
    <type 
        name="eop_basedata_budget_dimension">
        <value-label>
            <value>1</value>
            <label-key>enums.budget_dimension.1</label-key>
            <bundle>eop-basedata</bundle>
        </value-label>
        <value-label>
            <value>2</value>
            <label-key>enums.budget_dimension.2</label-key>
            <bundle>eop-basedata</bundle>
        </value-label>
        <value-label>
            <value>3</value>
            <label-key>enums.budget_dimension.3</label-key>
            <bundle>eop-basedata</bundle>
        </value-label>
        <value-label>
            <value>4</value>
            <label-key>enums.budget_dimension.4</label-key>
            <bundle>eop-basedata</bundle>
        </value-label>
        <value-label>
            <value>5</value>
            <label-key>enums.budget_dimension.5</label-key>
            <bundle>eop-basedata</bundle>
        </value-label>
        <value-label>
            <value>6</value>
            <label-key>enums.budget_dimension.6</label-key>
            <bundle>eop-basedata</bundle>
        </value-label>
        <value-label>
            <value>7</value>
            <label-key>enums.budget_dimension.7</label-key>
            <bundle>eop-basedata</bundle>
        </value-label>
        <value-label>
            <value>8</value>
            <label-key>enums.budget_dimension.8</label-key>
            <bundle>eop-basedata</bundle>
        </value-label>
        <!-- <value-label>
            <value>9</value>
            <label-key>enums.budget_dimension.9</label-key>
            <bundle>eop-basedata</bundle>
        </value-label> -->
        <value-label>
            <value>10</value>
            <label-key>enums.budget_dimension.10</label-key>
            <bundle>eop-basedata</bundle>
        </value-label>
        <value-label>
            <value>11</value>
            <label-key>enums.budget_dimension.11</label-key>
            <bundle>eop-basedata</bundle>
        </value-label>
    </type>
    <type 
        name="eop_basedata_budget_dimension_ekp">
        <value-label>
            <value>2</value>
            <label-key>enums.budget_dimension.2</label-key>
            <bundle>eop-basedata</bundle>
        </value-label>
        <value-label>
            <value>3</value>
            <label-key>enums.budget_dimension.3</label-key>
            <bundle>eop-basedata</bundle>
        </value-label>
        <value-label>
            <value>4</value>
            <label-key>enums.budget_dimension.4</label-key>
            <bundle>eop-basedata</bundle>
        </value-label>
        <value-label>
            <value>8</value>
            <label-key>enums.budget_dimension.8</label-key>
            <bundle>eop-basedata</bundle>
        </value-label>
    </type>
    <type 
        name="eop_basedata_supplier_area_type" default-value="0">
        <value-label>
            <value>0</value>
            <label-key>enums.supplier.type1</label-key>
            <bundle>eop-basedata</bundle>
        </value-label>
        <value-label>
            <value>1</value>
            <label-key>enums.supplier.type2</label-key>
            <bundle>eop-basedata</bundle>
        </value-label>
    </type>
    <type 
        name="eop_basedata_open_close_type">
        <value-label>
            <value>1</value>
            <label-key>enums.accounts.open</label-key>
            <bundle>eop-basedata</bundle>
        </value-label>
        <value-label>
            <value>0</value>
            <label-key>enums.accounts.close</label-key>
            <bundle>eop-basedata</bundle>
        </value-label>
    </type>
    <type 
        name="eop_basedata_project_type">
        <value-label>
            <value>1</value>
            <label-key>enums.project.type1</label-key>
            <bundle>eop-basedata</bundle>
        </value-label>
        <value-label>
            <value>2</value>
            <label-key>enums.project.type2</label-key>
            <bundle>eop-basedata</bundle>
        </value-label>
        <value-label>
            <value>3</value>
            <label-key>enums.project.type3</label-key>
            <bundle>eop-basedata</bundle>
        </value-label>
    </type>
    <type 
        name="eop_basedata_company_type">
        <value-label>
            <value>1</value>
            <label-key>enums.company.type1</label-key>
            <bundle>eop-basedata</bundle>
        </value-label>
        <value-label>
            <value>2</value>
            <label-key>enums.company.type2</label-key>
            <bundle>eop-basedata</bundle>
        </value-label>
    </type>
    <type
        name="eop_basedata_budgeting_type">
        <value-label>
            <value>1</value>
            <label-key>enums.budgeting.type.up.to.down</label-key>
            <bundle>eop-basedata</bundle>
        </value-label>
        <value-label>
            <value>2</value>
            <label-key>enums.budgeting.type.down.to.up</label-key>
            <bundle>eop-basedata</bundle>
        </value-label>
        <value-label>
            <value>3</value>
            <label-key>enums.budgeting.type.independent</label-key>
            <bundle>eop-basedata</bundle>
        </value-label>
    </type>
    <type
        name="eop_basedata_trip_type">
        <value-label>
            <value>1</value>
            <label-key>enums.trip.type.1</label-key>
            <bundle>eop-basedata</bundle>
        </value-label>
        <value-label>
            <value>2</value>
            <label-key>enums.trip.type.2</label-key>
            <bundle>eop-basedata</bundle>
        </value-label>
    </type>
    <type
            name="eop_basedata_day_cal_type">
        <value-label>
            <value>1</value>
            <label-key>enums.day.cal.type.1</label-key>
            <bundle>eop-basedata</bundle>
        </value-label>
        <value-label>
            <value>2</value>
            <label-key>enums.day.cal.type.2</label-key>
            <bundle>eop-basedata</bundle>
        </value-label>
    </type>
    <type 
        name="eop_basedata_supplier_area">
        <value-label>
            <value>0</value>
            <label-key>enums.supplier_area.0</label-key>
            <bundle>eop-basedata</bundle>
        </value-label>
        <value-label>
            <value>1</value>
            <label-key>enums.supplier_area.1</label-key>
            <bundle>eop-basedata</bundle>
        </value-label>
    </type>
    <type 
        name="eop_basedata_material_status">
        <value-label>
            <value>1</value>
            <label-key>enums.material_status.1</label-key>
            <bundle>eop-basedata</bundle>
        </value-label>
        <value-label>
            <value>2</value>
            <label-key>enums.material_status.2</label-key>
            <bundle>eop-basedata</bundle>
        </value-label>
    </type>
    <type 
        name="fs_base_pay_bank_belong">
         <value-label>
            <value>0</value>
            <label-key>enums.paybankbelong.0</label-key>
            <bundle>eop-basedata</bundle>
        </value-label>
        <value-label>
            <value>1</value>
            <label-key>enums.paybankbelong.1</label-key>
            <bundle>eop-basedata</bundle>
        </value-label>
        <value-label>
            <value>2</value>
            <label-key>enums.paybankbelong.2</label-key>
            <bundle>eop-basedata</bundle>
        </value-label>
        <value-label>
            <value>4</value>
            <label-key>enums.paybankbelong.4</label-key>
            <bundle>eop-basedata</bundle>
        </value-label>
	<value-label>
            <value>5</value>
            <label-key>enums.paybankbelong.5</label-key>
            <bundle>eop-basedata</bundle>
        </value-label>
    </type>
    
      <type 
        name="fs_base_skip_flag">
         <value-label>
            <value>Y</value>
            <label-key>enums.fdSkipFlag.Y</label-key>
            <bundle>eop-basedata</bundle>
        </value-label>
        <value-label>
            <value>N</value>
            <label-key>enums.fdSkipFlag.N</label-key>
            <bundle>eop-basedata</bundle>
        </value-label>
    </type>
     <type 
        name="eop_basedata_payment_status">
         <value-label>
            <value>10</value>
            <label-key>enums.fd_payment_status.10</label-key>
            <bundle>eop-basedata</bundle>
        </value-label>
        <value-label>
            <value>11</value>
            <label-key>enums.fd_payment_status.11</label-key>
            <bundle>eop-basedata</bundle>
        </value-label>
        <value-label>
            <value>20</value>
            <label-key>enums.fd_payment_status.20</label-key>
            <bundle>eop-basedata</bundle>
        </value-label>
        <value-label>
            <value>30</value>
            <label-key>enums.fd_payment_status.30</label-key>
            <bundle>eop-basedata</bundle>
        </value-label>
        <value-label>
            <value>50</value>
            <label-key>enums.fd_payment_status.50</label-key>
            <bundle>eop-basedata</bundle>
        </value-label>
        <value-label>
            <value>51</value>
            <label-key>enums.fd_payment_status.51</label-key>
            <bundle>eop-basedata</bundle>
        </value-label>
    </type>
     <type 
        name="eop_basedata_fd_bookkeeping_status">
         <value-label>
            <value>10</value>
            <label-key>enums.bookkeeping_status.10</label-key>
            <bundle>eop-basedata</bundle>
        </value-label>
          <value-label>
            <value>11</value>
            <label-key>enums.bookkeeping_status.11</label-key>
            <bundle>eop-basedata</bundle>
        </value-label>
        <value-label>
            <value>20</value>
            <label-key>enums.bookkeeping_status.20</label-key>
            <bundle>eop-basedata</bundle>
        </value-label>
        <value-label>
            <value>30</value>
            <label-key>enums.bookkeeping_status.30</label-key>
            <bundle>eop-basedata</bundle>
        </value-label>
    </type>
    <type 
        name="eop_basedata_fd_voucher_status">
         <value-label>
            <value>10</value>
            <label-key>enums.voucher_status.10</label-key>
            <bundle>eop-basedata</bundle>
        </value-label>
         <value-label>
            <value>11</value>
            <label-key>enums.voucher_status.11</label-key>
            <bundle>eop-basedata</bundle>
        </value-label>
        <value-label>
            <value>20</value>
            <label-key>enums.voucher_status.20</label-key>
            <bundle>eop-basedata</bundle>
        </value-label>
         <value-label>
            <value>30</value>
            <label-key>enums.voucher_status.30</label-key>
            <bundle>eop-basedata</bundle>
        </value-label>
    </type>
     <type 
        name="eop_basedata_switch_useBank">
        <value-label>
            <value>CMB</value>
            <label-key>enums.switch.bank_CMB</label-key>
            <bundle>eop-basedata</bundle>
        </value-label>
        <value-label>
            <value>BOC</value>
            <label-key>enums.switch.bank_BOC</label-key>
            <bundle>eop-basedata</bundle>
        </value-label>
         <value-label>
             <value>CBS</value>
             <label-key>enums.switch.bank_CBS</label-key>
             <bundle>eop-basedata</bundle>
         </value-label>
	 <value-label>
        	<value>CMInt</value>
        	<label-key>enums.switch.bank_CMInt</label-key>
        	<bundle>eop-basedata</bundle>
        </value-label>
      </type>
     <type 
        name="eop_basedata_switch_passType">
        <value-label>
            <value>1</value>
            <label-key>enums.switch.notify</label-key>
            <bundle>eop-basedata</bundle>
        </value-label>
        <value-label>
            <value>2</value>
            <label-key>enums.switch.pass</label-key>
            <bundle>eop-basedata</bundle>
        </value-label>
      </type>  
     <type 
        name="eop_basedata_budget_dedu_rule">
        <value-label>
            <value>1</value>
            <label-key>enums.switch.dedu.rule.havetax</label-key>
            <bundle>eop-basedata</bundle>
        </value-label>
        <value-label>
            <value>2</value>
            <label-key>enums.switch.dedu.rule.notax</label-key>
            <bundle>eop-basedata</bundle>
        </value-label>
      </type>  
      <type 
        name="eop_basedata_supplier_customer">
        <value-label>
            <value>1</value>
            <label-key>enums.supplier</label-key>
            <bundle>eop-basedata</bundle>
        </value-label>
        <value-label>
            <value>2</value>
            <label-key>enums.customer</label-key>
            <bundle>eop-basedata</bundle>
        </value-label>
      </type>
	  <!-- 款项类型 -->
	  <type name="eop_basedata_fund_type">
        <value-label>
            <value>00</value>
            <label-key>enums.fund_type.00</label-key>
            <bundle>eop-basedata</bundle>
        </value-label>
        <value-label>
            <value>01</value>
            <label-key>enums.fund_type.01</label-key>
            <bundle>eop-basedata</bundle>
        </value-label>
    </type>
    <!-- 开卡标识 -->
    <type name="eop_basedata_cardInfo_activationCode">
        <value-label>
            <value>Y</value>
            <label-key>enums.cardInfo_activationCode.Y</label-key>
            <bundle>eop-basedata</bundle>
        </value-label>
        <value-label>
            <value>N</value>
            <label-key>enums.cardInfo_activationCode.N</label-key>
            <bundle>eop-basedata</bundle>
        </value-label>
    </type>
    <!-- 流通状态 -->
    <type name="eop_basedata_cardInfo_circulationFlag">
        <value-label>
            <value>Y</value>
            <label-key>enums.cardInfo_circulationFlag.Y</label-key>
            <bundle>eop-basedata</bundle>
        </value-label>
        <value-label>
            <value>N</value>
            <label-key>enums.cardInfo_circulationFlag.N</label-key>
            <bundle>eop-basedata</bundle>
        </value-label>
    </type>
    <type name="eop_basedata_is_tax">
        <value-label>
            <value>1</value>
            <label-key>enums.is_tax.1</label-key>
            <bundle>eop-basedata</bundle>
        </value-label>
        <value-label>
            <value>0</value>
            <label-key>enums.is_tax.0</label-key>
            <bundle>eop-basedata</bundle>
        </value-label>
    </type>
    <type name="eop_basedata_receiver_type">
        <value-label>
            <value>1</value>
            <label-key>enums.receiver.type1</label-key>
            <bundle>eop-basedata</bundle>
        </value-label>
        <value-label>
            <value>2</value>
            <label-key>enums.receiver.type2</label-key>
            <bundle>eop-basedata</bundle>
        </value-label>
    </type>
    <type
        name="eop_basedata_bill_status">
        <value-label>
            <value>01</value>
            <label-key>enums.fd_bill_status.01</label-key>
            <bundle>eop-basedata</bundle>
        </value-label>
        <value-label>
            <value>02</value>
            <label-key>enums.fd_bill_status.02</label-key>
            <bundle>eop-basedata</bundle>
        </value-label>
        <value-label>
            <value>03</value>
            <label-key>enums.fd_bill_status.03</label-key>
            <bundle>eop-basedata</bundle>
        </value-label>
        <value-label>
            <value>04</value>
            <label-key>enums.fd_bill_status.04</label-key>
            <bundle>eop-basedata</bundle>
        </value-label>
        <value-label>
            <value>05</value>
            <label-key>enums.fd_bill_status.05</label-key>
            <bundle>eop-basedata</bundle>
        </value-label>
        <value-label>
            <value>06</value>
            <label-key>enums.fd_bill_status.06</label-key>
            <bundle>eop-basedata</bundle>
        </value-label>
    </type>
    <type
        name="eop_basedata_cabinet_type">
        <value-label>
            <value>inhand</value>
            <label-key>enums.cabinet_type.inhand</label-key>
            <bundle>eop-basedata</bundle>
        </value-label>
    </type>
</column-enums>
