{
    "global":     {
        "modelName": "com.landray.kmss.dbcenter.echarts.model.DbEchartsTemplate",
        "messageKey": "dbcenter-echarts:table.dbEchartsTemplate",
        "displayProperty": "fdName",
        "serviceBean": "dbEchartsTemplateService",
        "table": "db_echarts_template",
        "url": "/dbcenter/echarts/db_echarts_template/dbEchartsTemplate.do?method=view&fdId=${fdId}"
    },
    "attrs":     {
        "fdId":         {
            "propertyType": "id",
            "generator": {"type": "assigned"}
        },
        "fdName":         {
            "propertyType": "simple",
            "messageKey": "dbcenter-echarts:dbEchartsTemplate.fdName",
            "type": "String",
            "column": "fd_name",
            "notNull": "true",
            "length": "200",
            "validate": "true",
            "langSupport": "true"
        },
        "fdOrder":         {
            "propertyType": "simple",
            "messageKey": "dbcenter-echarts:dbEchartsTemplate.fdOrder",
            "type": "Integer",
            "column": "fd_order",
            "notNull": "false",
            "length": "10",
            "validate": "true"
        },
        "docCreateTime":         {
            "propertyType": "simple",
            "messageKey": "dbcenter-echarts:dbEchartsTemplate.docCreateTime",
            "type": "DateTime",
            "column": "doc_create_time",
            "notNull": "false",
            "validate": "false"
        },
        "fdHierarchyId":         {
            "propertyType": "simple",
            "messageKey": "dbcenter-echarts:dbEchartsTemplate.fdHierarchyId",
            "type": "String",
            "column": "fd_hierarchy_id",
            "notNull": "false",
            "length": "900",
            "validate": "false",
            "canDisplay": "false"
        },
        "docCreator":         {
            "propertyType": "model",
            "messageKey": "dbcenter-echarts:dbEchartsTemplate.docCreatorName",
            "type": "com.landray.kmss.sys.organization.model.SysOrgPerson",
            "column": "doc_creator_id",
            "notNull": "false",
            "validate": "false"
        },
        "docAlteror":         {
            "propertyType": "model",
            "messageKey": "dbcenter-echarts:dbEchartsTemplate.docAlteror",
            "type": "com.landray.kmss.sys.organization.model.SysOrgPerson",
            "column": "doc_alteror_id",
            "notNull": "false",
            "unique": "false"
        },
        "docAlterTime":         {
            "propertyType": "simple",
            "messageKey": "dbcenter-echarts:dbEchartsTemplate.docAlterTime",
            "type": "DateTime",
            "column": "doc_alter_time",
            "notNull": "false",
            "unique": "false"
        },
        "authTmpReaders":         {
            "propertyType": "list",
            "messageKey": "dbcenter-echarts:dbEchartsTemplate.authTmpReaders",
            "column": "fd_template_id",
            "type": "com.landray.kmss.sys.organization.model.SysOrgElement",
            "elementColumn": "auth_reader_id",
            "table": "db_echarts_tmp_def_reader",
            "canDisplay": "false"
        },
        "authTmpEditors":         {
            "propertyType": "list",
            "messageKey": "dbcenter-echarts:dbEchartsTemplate.authTmpEditors",
            "column": "fd_template_id",
            "type": "com.landray.kmss.sys.organization.model.SysOrgElement",
            "elementColumn": "auth_editor_id",
            "table": "db_echarts_tmp_def_editor",
            "canDisplay": "false"
        },
        "authReaderFlag":         {
            "propertyType": "simple",
            "messageKey": "dbcenter-echarts:dbEchartsTemplate.authReaderFlag",
            "type": "Boolean",
            "column": "auth_reader_flag",
            "notNull": "false",
            "unique": "false",
            "canDisplay": "false",
            "length": "1"
        },
        "authNotReaderFlag":         {
            "propertyType": "simple",
            "messageKey": "dbcenter-echarts:dbEchartsTemplate.authNotReaderFlag",
            "type": "Boolean",
            "column": "auth_not_reader_flag",
            "notNull": "false",
            "unique": "false",
            "length": "1",
            "canDisplay": "false"
        },
        "authReaders":         {
            "propertyType": "list",
            "messageKey": "dbcenter-echarts:dbEchartsTemplate.authReaders",
            "column": "fd_template_id",
            "type": "com.landray.kmss.sys.organization.model.SysOrgElement",
            "elementColumn": "auth_reader_id",
            "table": "db_echarts_tmp_reader"
        },
        "authOtherReaders":         {
            "propertyType": "list",
            "messageKey": "dbcenter-echarts:dbEchartsTemplate.authOtherReaders",
            "column": "fd_template_id",
            "type": "com.landray.kmss.sys.organization.model.SysOrgElement",
            "elementColumn": "auth_other_reader_id",
            "table": "db_echarts_tmp_oreader",
            "canDisplay": "false"
        },
        "authAllReaders":         {
            "propertyType": "list",
            "messageKey": "dbcenter-echarts:dbEchartsTemplate.authAllReaders",
            "column": "fd_template_id",
            "type": "com.landray.kmss.sys.organization.model.SysOrgElement",
            "elementColumn": "auth_all_reader_id",
            "table": "db_echarts_tmp_areader",
            "canDisplay": "false"
        },
        "authEditors":         {
            "propertyType": "list",
            "messageKey": "dbcenter-echarts:dbEchartsTemplate.authEditors",
            "column": "fd_template_id",
            "type": "com.landray.kmss.sys.organization.model.SysOrgElement",
            "elementColumn": "auth_editor_id",
            "table": "db_echarts_tmp_editor"
        },
        "authOtherEditors":         {
            "propertyType": "list",
            "messageKey": "dbcenter-echarts:dbEchartsTemplate.authOtherEditors",
            "column": "fd_template_id",
            "type": "com.landray.kmss.sys.organization.model.SysOrgElement",
            "elementColumn": "auth_other_editor_id",
            "table": "db_echarts_tmp_oeditor",
            "canDisplay": "false"
        },
        "authAllEditors":         {
            "propertyType": "list",
            "messageKey": "sys-right:right.edit.authAllEditors",
            "column": "fd_template_id",
            "type": "com.landray.kmss.sys.organization.model.SysOrgElement",
            "elementColumn": "auth_all_editor_id",
            "table": "db_echarts_tmp_aeditor",
            "canDisplay": "false"
        },
        "hbmParent":         {
            "propertyType": "model",
            "type": "com.landray.kmss.dbcenter.echarts.model.DbEchartsTemplate",
            "column": "fd_parent_id"
        }
    }
}